TensorflowTutorialsNlintz/README.md
TensorflowTutorialsNlintz/__init__.py
TensorflowTutorialsNlintz/__main__.py
TensorflowTutorialsNlintz/file.epub
TensorflowTutorialsNlintz/index.html
TensorflowTutorialsNlintz/css/__init__.py
TensorflowTutorialsNlintz/css/annotations.css
TensorflowTutorialsNlintz/css/main.css
TensorflowTutorialsNlintz/css/normalize.css
TensorflowTutorialsNlintz/css/popup.css
TensorflowTutorialsNlintz/font/__init__.py
TensorflowTutorialsNlintz/font/fontello.eot
TensorflowTutorialsNlintz/font/fontello.svg
TensorflowTutorialsNlintz/font/fontello.ttf
TensorflowTutorialsNlintz/font/fontello.woff
TensorflowTutorialsNlintz/img/__init__.py
TensorflowTutorialsNlintz/img/annotator-glyph-sprite.png
TensorflowTutorialsNlintz/img/annotator-icon-sprite.png
TensorflowTutorialsNlintz/img/apple-touch-icon.png
TensorflowTutorialsNlintz/img/cancelfullscreen.png
TensorflowTutorialsNlintz/img/close.png
TensorflowTutorialsNlintz/img/fullscreen.png
TensorflowTutorialsNlintz/img/loader.gif
TensorflowTutorialsNlintz/img/menu-icon.png
TensorflowTutorialsNlintz/img/save.png
TensorflowTutorialsNlintz/img/saved.png
TensorflowTutorialsNlintz/img/settings-s.png
TensorflowTutorialsNlintz/img/settings.png
TensorflowTutorialsNlintz/img/star.png
TensorflowTutorialsNlintz/js/__init__.py
TensorflowTutorialsNlintz/js/epub.js
TensorflowTutorialsNlintz/js/epub.min.js
TensorflowTutorialsNlintz/js/epub.min.map
TensorflowTutorialsNlintz/js/hooks.min.js
TensorflowTutorialsNlintz/js/hooks.min.map
TensorflowTutorialsNlintz/js/reader.js
TensorflowTutorialsNlintz/js/reader.js.map
TensorflowTutorialsNlintz/js/reader.min.js
TensorflowTutorialsNlintz/js/reader.min.map
TensorflowTutorialsNlintz/js/hooks/__init__.py
TensorflowTutorialsNlintz/js/hooks/extensions/__init__.py
TensorflowTutorialsNlintz/js/hooks/extensions/highlight.js
TensorflowTutorialsNlintz/js/libs/__init__.py
TensorflowTutorialsNlintz/js/libs/jquery.min.js
TensorflowTutorialsNlintz/js/libs/localforage.min.js
tensorflow_tutorials_nlintz-2024.3.3.0.dist-info/METADATA
tensorflow_tutorials_nlintz-2024.3.3.0.dist-info/WHEEL
tensorflow_tutorials_nlintz-2024.3.3.0.dist-info/entry_points.txt
tensorflow_tutorials_nlintz-2024.3.3.0.dist-info/top_level.txt
tensorflow_tutorials_nlintz-2024.3.3.0.dist-info/RECORD
